winpy/__init__.py
winpy/base/__init__.py
winpy/base/win.py
winpy-0.1.2.3.dist-info/METADATA
winpy-0.1.2.3.dist-info/WHEEL
winpy-0.1.2.3.dist-info/top_level.txt
winpy-0.1.2.3.dist-info/RECORD
