Metadata-Version: 2.1
Name: winpy
Version: 0.1.2.3
Summary: The Win32 CPython Functions
Home-page: http://www.wylib.com/py/lib/
Author: WYQ
Author-email: wyqlib@qq.com
Maintainer: WYQ
Maintainer-email: wyqlib@qq.com
License: MIT
Download-URL: http://www.wyqlib.com/py/lib
Keywords: tool utils lib
Platform: UNKNOWN
Requires-Python: >=3.6
Requires-Dist: wyqpy
